LICENSE
MANIFEST.in
README
distribute_setup.py
setup.py
gmm_specializer/__init__.py
gmm_specializer/gmm.py
gmm_specializer.egg-info/PKG-INFO
gmm_specializer.egg-info/SOURCES.txt
gmm_specializer.egg-info/dependency_links.txt
gmm_specializer.egg-info/requires.txt
gmm_specializer.egg-info/top_level.txt
tests/em_convert_from_pickle_dump_to_csv.py
tests/gmm_test.py