Metadata-Version: 1.0
Name: gmm-specializer
Version: 0.1
Summary: This is a SEJITS (selective embedded just-in-time specializer) for Gaussian Mixture Models, built on the ASP framework.
Home-page: http://github.com/hcook/gmm/wiki/
Author: Henry Cook, Katya Gonina, Shoaib Kamil
Author-email: egonina@cs.berkeley.edu
License: BSD
Platform: UNKNOWN
Classifier: Development Status :: 2 - Pre-Alpha
Classifier: Intended Audience :: Developers
Classifier: Intended Audience :: Other Audience
Classifier: Intended Audience :: Science/Research
Classifier: License :: OSI Approved :: BSD License
Classifier: Natural Language :: English
Classifier: Programming Language :: Python
Classifier: Topic :: Scientific/Engineering
Classifier: Topic :: Software Development :: Libraries
Classifier: Topic :: Utilities
